commandante
