Metadata-Version: 1.1
Name: commandante
Version: 0.2.6
Summary: Find and fix missing trailing commas in Python collections.
Home-page: https://github.com/lensvol/commandante
Author: Kirill Borisov
Author-email: lensvol@gmail.com
License: MIT
Keywords: commandante
Platform: UNKNOWN
Classifier: Development Status :: 3 - Alpha
Classifier: Topic :: Utilities
Classifier: License :: OSI Approved :: MIT License
Classifier: Programming Language :: Python :: 2
Classifier: Programming Language :: Python :: 2.6
Classifier: Programming Language :: Python :: 2.7
Classifier: Operating System :: POSIX
